couchdb/json.py
couchdb/__main__.py
couchdb/multipart.py
couchdb/design.py
couchdb/client.py
couchdb/mapping.py
couchdb/view.py
couchdb/util.py
couchdb/http.py
couchdb/__init__.py
couchdb/util2.py
couchdb/util3.py
couchdb/tests/__main__.py
couchdb/tests/multipart.py
couchdb/tests/design.py
couchdb/tests/client.py
couchdb/tests/mapping.py
couchdb/tests/view.py
couchdb/tests/tools.py
couchdb/tests/package.py
couchdb/tests/__init__.py
couchdb/tests/testutil.py
couchdb/tests/couch_tests.py
couchdb/tests/couchhttp.py
couchdb/tools/replicate.py
couchdb/tools/dump.py
couchdb/tools/load.py
couchdb/tools/__init__.py
CouchDB-1.0.1.dist-info/metadata.json
CouchDB-1.0.1.dist-info/WHEEL
CouchDB-1.0.1.dist-info/entry_points.txt
CouchDB-1.0.1.dist-info/RECORD
CouchDB-1.0.1.dist-info/zip-safe
CouchDB-1.0.1.dist-info/DESCRIPTION.rst
CouchDB-1.0.1.dist-info/top_level.txt
CouchDB-1.0.1.dist-info/METADATA
